<?xml version="1.0" encoding="utf-8"?>
<data-map xmlns="http://cayenne.apache.org/schema/3.0/modelMap"
	 xmlns:xsi="http://www.w3.org/2001/XMLSchema-instance"
	 xsi:schemaLocation="http://cayenne.apache.org/schema/3.0/modelMap http://cayenne.apache.org/schema/3.0/modelMap.xsd"
	 project-version="6">
	<property name="defaultPackage" value="mc.andromeda.system.db"/>
	<db-entity name="cms_page" catalog="mydb">
		<db-attribute name="Description" type="VARCHAR" length="128"/>
		<db-attribute name="FieldLayout" type="VARCHAR" length="128"/>
		<db-attribute name="FormLayout" type="VARCHAR" length="128"/>
		<db-attribute name="ID" type="INTEGER" isPrimaryKey="true" isMandatory="true" length="11"/>
		<db-attribute name="LookAndFeel" type="VARCHAR" length="128"/>
		<db-attribute name="Name" type="VARCHAR" length="45"/>
		<db-attribute name="Path" type="VARCHAR" length="256"/>
		<db-attribute name="Title" type="VARCHAR" length="128"/>
		<db-attribute name="authorized_groups" type="VARCHAR" length="45"/>
		<db-attribute name="content" type="VARCHAR"/>
	</db-entity>
	<db-entity name="crontab">
		<db-attribute name="ClassPath" type="VARCHAR" length="128"/>
		<db-attribute name="Day" type="VARCHAR" length="256"/>
		<db-attribute name="Enabled" type="VARCHAR" isMandatory="true" length="3"/>
		<db-attribute name="Hour" type="VARCHAR" length="96"/>
		<db-attribute name="Minute" type="VARCHAR" length="256"/>
		<db-attribute name="Month" type="VARCHAR" length="96"/>
		<db-attribute name="Name" type="VARCHAR" isPrimaryKey="true" isMandatory="true" length="32"/>
		<db-attribute name="Weekday" type="VARCHAR" length="28"/>
	</db-entity>
	<db-entity name="group_membership" catalog="mydb">
		<db-attribute name="Created" type="TIMESTAMP" length="19"/>
		<db-attribute name="GroupID" type="INTEGER" isMandatory="true" length="11"/>
		<db-attribute name="ID" type="INTEGER" isPrimaryKey="true" isMandatory="true" length="11"/>
		<db-attribute name="UserID" type="INTEGER" isMandatory="true" length="11"/>
	</db-entity>
	<db-entity name="group_rights" catalog="ncr">
		<db-attribute name="group_id" type="INTEGER" length="11"/>
		<db-attribute name="id" type="INTEGER" isPrimaryKey="true" isMandatory="true" length="11"/>
		<db-attribute name="permission" type="VARCHAR" length="45"/>
		<db-attribute name="record_class" type="VARCHAR" length="45"/>
		<db-attribute name="record_id" type="INTEGER" length="11"/>
		<db-attribute name="record_type" type="VARCHAR" length="45"/>
	</db-entity>
	<db-entity name="navigation_link" catalog="mydb">
		<db-attribute name="Display" type="VARCHAR" length="45"/>
		<db-attribute name="Href" type="LONGVARCHAR" length="65535"/>
		<db-attribute name="ID" type="INTEGER" isPrimaryKey="true" isMandatory="true" length="11"/>
		<db-attribute name="OnMouseClick" type="LONGVARCHAR" length="65535"/>
		<db-attribute name="OnMouseDown" type="LONGVARCHAR" length="65535"/>
		<db-attribute name="OnMouseOut" type="LONGVARCHAR" length="65535"/>
		<db-attribute name="OnMouseOver" type="LONGVARCHAR" length="65535"/>
		<db-attribute name="OnMouseUp" type="LONGVARCHAR" length="65535"/>
		<db-attribute name="SectionID" type="INTEGER" length="11"/>
		<db-attribute name="SortOrder" type="INTEGER" length="11"/>
		<db-attribute name="Target" type="VARCHAR" length="64"/>
	</db-entity>
	<db-entity name="navigation_section" catalog="mydb">
		<db-attribute name="Display" type="VARCHAR" length="45"/>
		<db-attribute name="Href" type="LONGVARCHAR" length="65535"/>
		<db-attribute name="ID" type="INTEGER" isPrimaryKey="true" isMandatory="true" length="11"/>
		<db-attribute name="OnMouseClick" type="LONGVARCHAR" length="65535"/>
		<db-attribute name="OnMouseDown" type="LONGVARCHAR" length="65535"/>
		<db-attribute name="OnMouseOut" type="LONGVARCHAR" length="65535"/>
		<db-attribute name="OnMouseOver" type="LONGVARCHAR" length="65535"/>
		<db-attribute name="OnMouseUp" type="LONGVARCHAR" length="65535"/>
		<db-attribute name="SortOrder" type="INTEGER" length="11"/>
		<db-attribute name="Type" type="VARCHAR" length="45"/>
	</db-entity>
	<db-entity name="role">
		<db-attribute name="ID" type="INTEGER" isPrimaryKey="true" isMandatory="true"/>
		<db-attribute name="Name" type="VARCHAR" isMandatory="true" length="32"/>
	</db-entity>
	<db-entity name="session">
		<db-attribute name="Created" type="TIMESTAMP" isMandatory="true"/>
		<db-attribute name="Data" type="BLOB" isMandatory="true"/>
		<db-attribute name="Modified" type="TIMESTAMP" isMandatory="true"/>
		<db-attribute name="SessionID" type="VARCHAR" isPrimaryKey="true" isMandatory="true" length="255"/>
	</db-entity>
	<db-entity name="user" catalog="mydb">
		<db-attribute name="created" type="TIMESTAMP" length="19"/>
		<db-attribute name="deleted" type="TIMESTAMP" length="19"/>
		<db-attribute name="fail_count" type="INTEGER" length="11"/>
		<db-attribute name="id" type="INTEGER" isPrimaryKey="true" isMandatory="true" length="11"/>
		<db-attribute name="last_failure   " type="TIMESTAMP" length="19"/>
		<db-attribute name="last_login" type="TIMESTAMP" length="19"/>
		<db-attribute name="locked" type="TIMESTAMP" length="19"/>
		<db-attribute name="password" type="VARCHAR" isMandatory="true" length="45"/>
		<db-attribute name="username" type="VARCHAR" isMandatory="true" length="32"/>
	</db-entity>
	<db-entity name="user_account" catalog="ncr">
		<db-attribute name="Password" type="VARCHAR" length="128"/>
		<db-attribute name="created" type="TIMESTAMP" length="19"/>
		<db-attribute name="deleted" type="TIMESTAMP" length="19"/>
		<db-attribute name="fail_count" type="INTEGER" length="11"/>
		<db-attribute name="id" type="INTEGER" isPrimaryKey="true" isMandatory="true" length="11"/>
		<db-attribute name="last_failure" type="TIMESTAMP" length="19"/>
		<db-attribute name="last_login" type="TIMESTAMP" length="19"/>
		<db-attribute name="locked" type="TIMESTAMP" length="19"/>
		<db-attribute name="username" type="VARCHAR" length="45"/>
	</db-entity>
	<db-entity name="user_attributes" catalog="ncr">
		<db-attribute name="data_type" type="VARCHAR" length="45"/>
		<db-attribute name="encoding" type="VARCHAR" length="45"/>
		<db-attribute name="id" type="INTEGER" isPrimaryKey="true" isMandatory="true" length="11"/>
		<db-attribute name="last_write" type="TIMESTAMP" length="19"/>
		<db-attribute name="name" type="VARCHAR" length="45"/>
		<db-attribute name="primitive_value" type="LONGVARCHAR" length="65535"/>
		<db-attribute name="raw_value" type="LONGVARBINARY" length="2147483647"/>
		<db-attribute name="user_id" type="INTEGER" length="11"/>
	</db-entity>
	<db-entity name="user_group" catalog="mydb">
		<db-attribute name="Created" type="TIMESTAMP" length="19"/>
		<db-attribute name="Deleted" type="TIMESTAMP" length="19"/>
		<db-attribute name="Description" type="LONGVARCHAR" length="65535"/>
		<db-attribute name="ID" type="INTEGER" isPrimaryKey="true" isMandatory="true" length="11"/>
		<db-attribute name="Name" type="VARCHAR" length="45"/>
	</db-entity>
	<obj-entity name="CmsPage" className="mc.andromeda.system.db.CmsPage" dbEntityName="cms_page">
		<obj-attribute name="authorizedGroups" type="java.lang.String" db-attribute-path="authorized_groups"/>
		<obj-attribute name="content" type="java.lang.String" db-attribute-path="content"/>
		<obj-attribute name="description" type="java.lang.String" db-attribute-path="Description"/>
		<obj-attribute name="fieldLayout" type="java.lang.String" db-attribute-path="FieldLayout"/>
		<obj-attribute name="formLayout" type="java.lang.String" db-attribute-path="FormLayout"/>
		<obj-attribute name="id" type="java.lang.Integer" db-attribute-path="ID"/>
		<obj-attribute name="lookAndFeel" type="java.lang.String" db-attribute-path="LookAndFeel"/>
		<obj-attribute name="name" type="java.lang.String" db-attribute-path="Name"/>
		<obj-attribute name="path" type="java.lang.String" db-attribute-path="Path"/>
		<obj-attribute name="title" type="java.lang.String" db-attribute-path="Title"/>
	</obj-entity>
	<obj-entity name="Crontab" className="mc.andromeda.system.db.Crontab" dbEntityName="crontab">
		<obj-attribute name="classPath" type="java.lang.String" db-attribute-path="ClassPath"/>
		<obj-attribute name="day" type="java.lang.String" db-attribute-path="Day"/>
		<obj-attribute name="enabled" type="java.lang.String" db-attribute-path="Enabled"/>
		<obj-attribute name="hour" type="java.lang.String" db-attribute-path="Hour"/>
		<obj-attribute name="minute" type="java.lang.String" db-attribute-path="Minute"/>
		<obj-attribute name="month" type="java.lang.String" db-attribute-path="Month"/>
		<obj-attribute name="name" type="java.lang.String" db-attribute-path="Name"/>
		<obj-attribute name="weekday" type="java.lang.String" db-attribute-path="Weekday"/>
	</obj-entity>
	<obj-entity name="GroupMembership" className="mc.andromeda.system.db.GroupMembership" dbEntityName="group_membership">
		<obj-attribute name="created" type="java.util.Date" db-attribute-path="Created"/>
	</obj-entity>
	<obj-entity name="GroupRights" className="mc.andromeda.system.db.GroupRights" dbEntityName="group_rights">
		<obj-attribute name="groupId" type="java.lang.Integer" db-attribute-path="group_id"/>
		<obj-attribute name="permission" type="java.lang.String" db-attribute-path="permission"/>
		<obj-attribute name="recordClass" type="java.lang.String" db-attribute-path="record_class"/>
		<obj-attribute name="recordId" type="java.lang.Integer" db-attribute-path="record_id"/>
		<obj-attribute name="recordType" type="java.lang.String" db-attribute-path="record_type"/>
	</obj-entity>
	<obj-entity name="NavigationLink" className="mc.andromeda.system.db.NavigationLink" dbEntityName="navigation_link">
		<obj-attribute name="display" type="java.lang.String" db-attribute-path="Display"/>
		<obj-attribute name="href" type="java.lang.String" db-attribute-path="Href"/>
		<obj-attribute name="id" type="java.lang.Integer" db-attribute-path="ID"/>
		<obj-attribute name="onMouseClick" type="java.lang.String" db-attribute-path="OnMouseClick"/>
		<obj-attribute name="onMouseDown" type="java.lang.String" db-attribute-path="OnMouseDown"/>
		<obj-attribute name="onMouseOut" type="java.lang.String" db-attribute-path="OnMouseOut"/>
		<obj-attribute name="onMouseOver" type="java.lang.String" db-attribute-path="OnMouseOver"/>
		<obj-attribute name="onMouseUp" type="java.lang.String" db-attribute-path="OnMouseUp"/>
		<obj-attribute name="sortOrder" type="java.lang.Integer" db-attribute-path="SortOrder"/>
		<obj-attribute name="target" type="java.lang.String" db-attribute-path="Target"/>
	</obj-entity>
	<obj-entity name="NavigationSection" className="mc.andromeda.system.db.NavigationSection" dbEntityName="navigation_section">
		<obj-attribute name="display" type="java.lang.String" db-attribute-path="Display"/>
		<obj-attribute name="href" type="java.lang.String" db-attribute-path="Href"/>
		<obj-attribute name="id" type="java.lang.Integer" db-attribute-path="ID"/>
		<obj-attribute name="onMouseClick" type="java.lang.String" db-attribute-path="OnMouseClick"/>
		<obj-attribute name="onMouseDown" type="java.lang.String" db-attribute-path="OnMouseDown"/>
		<obj-attribute name="onMouseOut" type="java.lang.String" db-attribute-path="OnMouseOut"/>
		<obj-attribute name="onMouseOver" type="java.lang.String" db-attribute-path="OnMouseOver"/>
		<obj-attribute name="onMouseUp" type="java.lang.String" db-attribute-path="OnMouseUp"/>
		<obj-attribute name="sortOrder" type="java.lang.Integer" db-attribute-path="SortOrder"/>
		<obj-attribute name="type" type="java.lang.String" db-attribute-path="Type"/>
	</obj-entity>
	<obj-entity name="Session" className="mc.andromeda.system.db.Session" dbEntityName="session">
		<obj-attribute name="created" type="java.util.Date" db-attribute-path="Created"/>
		<obj-attribute name="data" type="byte[]" db-attribute-path="Data"/>
		<obj-attribute name="modified" type="java.util.Date" db-attribute-path="Modified"/>
	</obj-entity>
	<obj-entity name="User" className="mc.andromeda.system.db.User" dbEntityName="user">
		<obj-attribute name="created" type="java.util.Date" db-attribute-path="created"/>
		<obj-attribute name="deleted" type="java.util.Date" db-attribute-path="deleted"/>
		<obj-attribute name="failCount" type="java.lang.Integer" db-attribute-path="fail_count"/>
		<obj-attribute name="id" type="java.lang.Integer" db-attribute-path="id"/>
		<obj-attribute name="lastFailure" type="java.util.Date" db-attribute-path="last_failure   "/>
		<obj-attribute name="lastLogin" type="java.util.Date" db-attribute-path="last_login"/>
		<obj-attribute name="locked" type="java.util.Date" db-attribute-path="locked"/>
		<obj-attribute name="password" type="java.lang.String" db-attribute-path="password"/>
		<obj-attribute name="username" type="java.lang.String" db-attribute-path="username"/>
	</obj-entity>
	<obj-entity name="UserAccount" className="mc.andromeda.system.db.UserAccount" dbEntityName="user_account">
		<obj-attribute name="created" type="java.util.Date" db-attribute-path="created"/>
		<obj-attribute name="deleted" type="java.util.Date" db-attribute-path="deleted"/>
		<obj-attribute name="failCount" type="java.lang.Integer" db-attribute-path="fail_count"/>
		<obj-attribute name="id" type="java.lang.Integer" db-attribute-path="id"/>
		<obj-attribute name="lastFailure" type="java.util.Date" db-attribute-path="last_failure"/>
		<obj-attribute name="lastLogin" type="java.util.Date" db-attribute-path="last_login"/>
		<obj-attribute name="locked" type="java.util.Date" db-attribute-path="locked"/>
		<obj-attribute name="password" type="java.lang.String" db-attribute-path="Password"/>
		<obj-attribute name="username" type="java.lang.String" db-attribute-path="username"/>
	</obj-entity>
	<obj-entity name="UserAttributes" className="mc.andromeda.system.db.UserAttributes" dbEntityName="user_attributes">
		<obj-attribute name="dataType" type="java.lang.String" db-attribute-path="data_type"/>
		<obj-attribute name="encoding" type="java.lang.String" db-attribute-path="encoding"/>
		<obj-attribute name="id" type="java.lang.Integer" db-attribute-path="id"/>
		<obj-attribute name="lastWrite" type="java.util.Date" db-attribute-path="last_write"/>
		<obj-attribute name="name" type="java.lang.String" db-attribute-path="name"/>
		<obj-attribute name="primitiveValue" type="java.lang.String" db-attribute-path="primitive_value"/>
		<obj-attribute name="rawValue" type="byte[]" db-attribute-path="raw_value"/>
	</obj-entity>
	<obj-entity name="UserGroup" className="mc.andromeda.system.db.UserGroup" dbEntityName="user_group">
		<obj-attribute name="created" type="java.util.Date" db-attribute-path="Created"/>
		<obj-attribute name="deleted" type="java.util.Date" db-attribute-path="Deleted"/>
		<obj-attribute name="description" type="java.lang.String" db-attribute-path="Description"/>
		<obj-attribute name="id" type="java.lang.Integer" db-attribute-path="ID"/>
		<obj-attribute name="name" type="java.lang.String" db-attribute-path="Name"/>
	</obj-entity>
	<db-relationship name="Group" source="group_membership" target="user_group" toMany="false">
		<db-attribute-pair source="GroupID" target="ID"/>
	</db-relationship>
	<db-relationship name="User" source="group_membership" target="user" toMany="false">
		<db-attribute-pair source="UserID" target="id"/>
	</db-relationship>
	<db-relationship name="group" source="group_rights" target="user_group" toMany="false">
		<db-attribute-pair source="group_id" target="ID"/>
	</db-relationship>
	<db-relationship name="section" source="navigation_link" target="navigation_section" toMany="false">
		<db-attribute-pair source="SectionID" target="ID"/>
	</db-relationship>
	<db-relationship name="links" source="navigation_section" target="navigation_link" toMany="true">
		<db-attribute-pair source="ID" target="SectionID"/>
	</db-relationship>
	<db-relationship name="GroupMemberships" source="user" target="group_membership" toMany="true">
		<db-attribute-pair source="id" target="UserID"/>
	</db-relationship>
	<db-relationship name="UserAttributes" source="user" target="user_attributes" toMany="true">
		<db-attribute-pair source="id" target="user_id"/>
	</db-relationship>
	<db-relationship name="User" source="user_attributes" target="user" toMany="false">
		<db-attribute-pair source="user_id" target="id"/>
	</db-relationship>
	<db-relationship name="UserMembership" source="user_group" target="group_membership" toMany="true">
		<db-attribute-pair source="ID" target="GroupID"/>
	</db-relationship>
	<db-relationship name="rights" source="user_group" target="group_rights" toMany="true">
		<db-attribute-pair source="ID" target="group_id"/>
	</db-relationship>
	<obj-relationship name="group" source="GroupMembership" target="UserGroup" deleteRule="Nullify" db-relationship-path="Group"/>
	<obj-relationship name="user" source="GroupMembership" target="User" deleteRule="Nullify" db-relationship-path="User"/>
	<obj-relationship name="group" source="GroupRights" target="UserGroup" deleteRule="Nullify" db-relationship-path="group"/>
	<obj-relationship name="section" source="NavigationLink" target="NavigationSection" deleteRule="Nullify" db-relationship-path="section"/>
	<obj-relationship name="links" source="NavigationSection" target="NavigationLink" deleteRule="Deny" db-relationship-path="links"/>
	<obj-relationship name="groupMemberships" source="User" target="GroupMembership" deleteRule="Deny" db-relationship-path="GroupMemberships"/>
	<obj-relationship name="userAttributes" source="User" target="UserAttributes" deleteRule="Deny" db-relationship-path="UserAttributes"/>
	<obj-relationship name="user" source="UserAttributes" target="User" deleteRule="Nullify" db-relationship-path="User"/>
	<obj-relationship name="rights" source="UserGroup" target="GroupRights" deleteRule="Deny" db-relationship-path="rights"/>
	<obj-relationship name="userMembership" source="UserGroup" target="GroupMembership" deleteRule="Deny" db-relationship-path="UserMembership"/>
</data-map>
